LICENSE
README.md
pyproject.toml
src/limen/__init__.py
src/limen/config.py
src/limen/core.py
src/limen/deduction.py
src/limen/energy.py
src/limen/explanations.py
src/limen/grounding.py
src/limen/induction.py
src/limen/inference.py
src/limen/neurosymbolic_ilp.py
src/limen/orchestrator.py
src/limen/parallel.py
src/limen/printing.py
src/limen/sampling.py
src/limen/semantics.py
src/limen/storage.py
src/limen/storage_utils.py
src/limen/training.py
src/limen/truth_functions.py
src/limen/pipeline/__init__.py
src/limen/pipeline/ingestion.py
src/limen/pipeline/llm_client.py
src/limen/pipeline/prompts.py
src/limen/pipeline/query.py
src/limen/pipeline/response.py
src/limen/pipeline/schema.py
src/limen_ai.egg-info/PKG-INFO
src/limen_ai.egg-info/SOURCES.txt
src/limen_ai.egg-info/dependency_links.txt
src/limen_ai.egg-info/requires.txt
src/limen_ai.egg-info/top_level.txt