Metadata-Version: 2.4
Name: limen-ai
Version: 0.3.1
Summary: Łukasiewicz Interpretable Markov Engine for Neuralized AI
Author: Enrico Zanardo
License-Expression: AGPL-3.0-or-later
Requires-Python: >=3.10
License-File: LICENSE
Requires-Dist: numpy>=2.0
Requires-Dist: scipy>=1.10
Requires-Dist: torch>=2.0
Provides-Extra: dev
Requires-Dist: pytest>=9.0; extra == "dev"
Dynamic: license-file
